{"protocol":{"minReaderVersion":1,"minWriterVersion":2}}
{"metaData":{"id":"b1fae0c4-f16e-4389-85be-5a58cfeeb51c","name":null,"description":null,"format":{"provider":"parquet","options":{}},"schemaString":"{\"type\":\"struct\",\"fields\":[{\"name\":\"order_id\",\"type\":\"long\",\"nullable\":true,\"metadata\":{}},{\"name\":\"item_id\",\"type\":\"long\",\"nullable\":true,\"metadata\":{}},{\"name\":\"product_id\",\"type\":\"long\",\"nullable\":true,\"metadata\":{}},{\"name\":\"quantity\",\"type\":\"long\",\"nullable\":true,\"metadata\":{}},{\"name\":\"list_price\",\"type\":\"double\",\"nullable\":true,\"metadata\":{}},{\"name\":\"discount\",\"type\":\"double\",\"nullable\":true,\"metadata\":{}}]}","partitionColumns":[],"createdTime":1741311043032,"configuration":{}}}
{"add":{"path":"part-00001-6285fd13-643b-4229-9f0c-e223416ba7e1-c000.snappy.parquet","partitionValues":{},"size":29197,"modificationTime":1741311043045,"dataChange":true,"stats":"{\"numRecords\":4722,\"minValues\":{\"discount\":0.05,\"order_id\":1,\"quantity\":1,\"item_id\":1,\"product_id\":2,\"list_price\":89.99},\"maxValues\":{\"product_id\":315,\"item_id\":5,\"order_id\":1615,\"list_price\":11999.99,\"discount\":0.2,\"quantity\":2},\"nullCount\":{\"discount\":0,\"list_price\":0,\"item_id\":0,\"product_id\":0,\"quantity\":0,\"order_id\":0}}","tags":null,"deletionVector":null,"baseRowId":null,"defaultRowCommitVersion":null,"clusteringProvider":null}}
{"commitInfo":{"timestamp":1741311043045,"operation":"WRITE","operationParameters":{"mode":"Overwrite"},"operationMetrics":{"execution_time_ms":22,"num_added_files":1,"num_added_rows":4722,"num_partitions":0,"num_removed_files":0},"clientVersion":"delta-rs.py-0.25.4"}}